fakedata/__init__.py
fakedata/fakedata.py
fakedata/list.py
FakeData-0.1.dist-info/LICENSE
FakeData-0.1.dist-info/METADATA
FakeData-0.1.dist-info/WHEEL
FakeData-0.1.dist-info/top_level.txt
FakeData-0.1.dist-info/RECORD
