Metadata-Version: 2.1
Name: FakeData
Version: 0.1
Summary: A python package for data fake generation
Home-page: https://github.com/Josecolin99/Data-Fake
Author: Jose Angel Colin Najera
Author-email: josecolin99@gmail.com
License: MIT
Platform: UNKNOWN
Classifier: Programming Language :: Python :: 3
Classifier: License :: OSI Approved :: MIT License
Classifier: Operating System :: OS Independent
License-File: LICENSE
